README
setup.py
charts/__init__.py
charts/gdchart2A.py
charts/genTriggers.py
charts/mosixChart.py
charts/mosixDataStore.py
charts/unittest_all.py
charts/unittest_genTriggers.py
charts/unittest_mosixChart.py
charts/unittest_mosixDataStore.py
charts/docs/diff_gdchart2a.txt
charts/test/.dump
charts/test/genTriggers_testdata.sql
charts/test/genTriggers_testdataComplex.sql
charts/test/genTriggers_testdataNOCASCADE.sql
charts/test/mosix-output-logfile.input
ez_setup/README.txt
ez_setup/__init__.py
fullChart.egg-info/PKG-INFO
fullChart.egg-info/SOURCES.txt
fullChart.egg-info/not-zip-safe
fullChart.egg-info/top_level.txt
