Metadata-Version: 1.0
Name: fullChart
Version: 0.1
Summary: generate charts (using gdchart) from mosix log files
Home-page: UNKNOWN
Author: Todd D. Greenwood
Author-email: t.greenwoodgeer@gmail.com
License: GNU Lesser General Public License
Platform: UNKNOWN
Classifier: Development Status :: 3 - Alpha
Classifier: Intended Audience :: Developers
Classifier: License :: OSI Approved :: GNU Library or Lesser General Public License (LGPL)
Classifier: Programming Language :: Python
Classifier: Topic :: Database :: Front-Ends
